puft/__init__.py
puft/__main__.py
puft/conftest.py
puft/__pycache__/__init__.cpython-310.pyc
puft/__pycache__/__main__.cpython-310.pyc
puft/__pycache__/conftest.cpython-310-pytest-7.1.2.pyc
puft/assets/logo.png
puft/constants/__pycache__/enums.cpython-310.pyc
puft/constants/__pycache__/hints.cpython-310.pyc
puft/constants/__pycache__/orm_types.cpython-310.pyc
puft/core/app/app_mode_enum.py
puft/core/app/http_method_enum.py
puft/core/app/puft.py
puft/core/app/puft_sv_ie.py
puft/core/app/turbo_action_enum.py
puft/core/app/__pycache__/app_mode_enum.cpython-310.pyc
puft/core/app/__pycache__/http_method_enum.cpython-310.pyc
puft/core/app/__pycache__/puft.cpython-310.pyc
puft/core/app/__pycache__/puft_sv_ie.cpython-310.pyc
puft/core/app/__pycache__/turbo_action_enum.cpython-310.pyc
puft/core/assembler/assembler.py
puft/core/assembler/assembler_test.py
puft/core/assembler/build.py
puft/core/assembler/config_extension_enum.py
puft/core/assembler/__pycache__/assembler.cpython-310.pyc
puft/core/assembler/__pycache__/assembler_test.cpython-310-pytest-7.1.2.pyc
puft/core/assembler/__pycache__/build.cpython-310.pyc
puft/core/assembler/__pycache__/config_extension_enum.cpython-310.pyc
puft/core/cell/cell.py
puft/core/cell/cell_error.py
puft/core/cell/__pycache__/cell.cpython-310.pyc
puft/core/cell/__pycache__/cell_error.cpython-310.pyc
puft/core/cli/cli.py
puft/core/cli/cli_db_enum.py
puft/core/cli/cli_helper_enum.py
puft/core/cli/cli_run_enum.py
puft/core/cli/__pycache__/cli_db_enum.cpython-310.pyc
puft/core/cli/__pycache__/cli_helper_enum.cpython-310.pyc
puft/core/cli/__pycache__/cli_run_enum.cpython-310.pyc
puft/core/db/db.py
puft/core/db/db_sv_ie.py
puft/core/db/db_type_enum.py
puft/core/db/model_not_found_error.py
puft/core/db/__pycache__/db.cpython-310.pyc
puft/core/db/__pycache__/db_sv_ie.cpython-310.pyc
puft/core/db/__pycache__/db_type_enum.cpython-310.pyc
puft/core/db/__pycache__/model_not_found_error.cpython-310.pyc
puft/core/emt/emt.py
puft/core/emt/emt_ie.py
puft-0.4.3.dist-info/METADATA
puft-0.4.3.dist-info/WHEEL
puft-0.4.3.dist-info/entry_points.txt
puft-0.4.3.dist-info/top_level.txt
puft-0.4.3.dist-info/RECORD
